cdk_cloudformation_poc_azure_blobstorage/__init__.py
cdk_cloudformation_poc_azure_blobstorage/py.typed
cdk_cloudformation_poc_azure_blobstorage/_jsii/__init__.py
cdk_cloudformation_poc_azure_blobstorage/_jsii/poc-azure-blobstorage@1.1.0-alpha.7.jsii.tgz
cdk_cloudformation_poc_azure_blobstorage-1.1.0a7.dist-info/LICENSE
cdk_cloudformation_poc_azure_blobstorage-1.1.0a7.dist-info/METADATA
cdk_cloudformation_poc_azure_blobstorage-1.1.0a7.dist-info/WHEEL
cdk_cloudformation_poc_azure_blobstorage-1.1.0a7.dist-info/top_level.txt
cdk_cloudformation_poc_azure_blobstorage-1.1.0a7.dist-info/RECORD
